neosca/__init__.py
neosca/__main__.py
neosca/about.py
neosca/depends_installer.py
neosca/main.py
neosca/neosca.py
neosca/parser.py
neosca/querier.py
neosca/scaenv.py
neosca/scaexceptions.py
neosca/scaio.py
neosca/scaplatform.py
neosca/scaprint.py
neosca/structure_counter.py
neosca/tregex_cli.py
neosca/util.py
neosca/data/anc_all_count.pickle.lzma
neosca/data/bnc_all_filtered.pickle.lzma
neosca/data/structure_data.json
neosca/lca/__init__.py
neosca/lca/__main__.py
neosca/lca/lca.py
neosca/lca/main.py
neosca-0.0.55.dist-info/LICENSE.txt
neosca-0.0.55.dist-info/METADATA
neosca-0.0.55.dist-info/WHEEL
neosca-0.0.55.dist-info/entry_points.txt
neosca-0.0.55.dist-info/top_level.txt
neosca-0.0.55.dist-info/RECORD
