Metadata-Version: 2.1
Name: neosca
Version: 0.0.55
Summary: Another syntactic complexity analyzer of written English language samples
Home-page: https://github.com/tanloong/neosca
Author: Long Tan
Author-email: tanloong@foxmail.com
License: UNKNOWN
Platform: UNKNOWN
Classifier: Programming Language :: Python :: 3.11
Classifier: Programming Language :: Python :: 3.10
Classifier: Programming Language :: Python :: 3.9
Classifier: Programming Language :: Python :: 3.8
Classifier: Programming Language :: Python :: 3.7
Classifier: Intended Audience :: Science/Research
Classifier: License :: OSI Approved :: GNU General Public License v2 or later (GPLv2+)
Classifier: Operating System :: MacOS
Classifier: Operating System :: POSIX :: Linux
Classifier: Operating System :: Microsoft :: Windows
Requires-Python: >=3.7
License-File: LICENSE.txt
Requires-Dist: JPype1
Requires-Dist: charset-normalizer
